dialogify/__init__.py
dialogify/_modidx.py
dialogify/core.py
dialogify-0.1.0.dist-info/licenses/LICENSE
dialogify-0.1.0.dist-info/METADATA
dialogify-0.1.0.dist-info/WHEEL
dialogify-0.1.0.dist-info/entry_points.txt
dialogify-0.1.0.dist-info/top_level.txt
dialogify-0.1.0.dist-info/RECORD
