Metadata-Version: 2.4
Name: dialogify
Version: 0.1.0
Summary: Easily turn HTML docs into solveit dialogs
Home-page: https://github.com/galopyz/dialogify
Author: Jay Suh
Author-email: shipalnomoo@gmail.com
License: Apache Software License 2.0
Keywords: nbdev jupyter notebook python solveit
Classifier: Development Status :: 4 - Beta
Classifier: Intended Audience :: Developers
Classifier: Natural Language :: English
Classifier: Programming Language :: Python :: 3.10
Classifier: Programming Language :: Python :: 3.11
Classifier: Programming Language :: Python :: 3.12
Classifier: License :: OSI Approved :: Apache Software License
Requires-Python: >=3.10
License-File: LICENSE
Requires-Dist: fastcore
Requires-Dist: dialoghelper
Requires-Dist: bs4
Requires-Dist: httpx
Provides-Extra: dev
Dynamic: author
Dynamic: author-email
Dynamic: classifier
Dynamic: description
Dynamic: description-content-type
Dynamic: home-page
Dynamic: keywords
Dynamic: license
Dynamic: license-file
Dynamic: provides-extra
Dynamic: requires-dist
Dynamic: requires-python
Dynamic: summary
